takopi_tunnel/__init__.py
takopi_tunnel/backend.py
takopi_tunnel-0.1.0.dist-info/METADATA
takopi_tunnel-0.1.0.dist-info/WHEEL
takopi_tunnel-0.1.0.dist-info/entry_points.txt
takopi_tunnel-0.1.0.dist-info/RECORD
