Metadata-Version: 2.4
Name: takopi-tunnel
Version: 0.1.0
Summary: Cloudflared tunnel management plugin for takopi
Requires-Python: >=3.14
Requires-Dist: takopi>=0.14
Provides-Extra: dev
Requires-Dist: pytest-asyncio>=0.24; extra == 'dev'
Requires-Dist: pytest>=8.0; extra == 'dev'
